{"created_time":"2023-12-31T10:06:48Z","files":[{"attachment_folder":"","created_time":"2025-11-04T01:31:41Z","id":"88","modified_time":"2025-11-04T01:31:41Z","name":"2PC.png","signature":"5621503432151619453","tags":[]},{"attachment_folder":"","created_time":"2025-11-04T01:31:41Z","id":"89","modified_time":"2025-11-04T01:31:41Z","name":"backwardRecovery.png","signature":"3986890418901571453","tags":[]},{"attachment_folder":"","created_time":"2025-11-04T01:31:41Z","id":"90","modified_time":"2025-11-04T01:31:41Z","name":"EventChoreographyo.png","signature":"5529866374996383613","tags":[]},{"attachment_folder":"","created_time":"2025-11-04T01:31:41Z","id":"91","modified_time":"2025-11-04T01:31:41Z","name":"fangxuangua.png","signature":"7793080107220424573","tags":[]},{"attachment_folder":"","created_time":"2025-11-04T01:31:41Z","id":"92","modified_time":"2025-11-04T01:31:41Z","name":"forwardRecovery.png","signature":"4541422622969780093","tags":[]},{"attachment_folder":"","created_time":"2025-11-04T01:31:41Z","id":"93","modified_time":"2025-11-04T01:31:41Z","name":"MQ.png","signature":"7128250462931343229","tags":[]},{"attachment_folder":"","created_time":"2025-11-04T01:31:41Z","id":"94","modified_time":"2025-11-04T01:31:41Z","name":"nullCancel.png","signature":"660964420298037117","tags":[]},{"attachment_folder":"","created_time":"2025-11-04T01:31:41Z","id":"95","modified_time":"2025-11-04T01:31:41Z","name":"OrderOrchestrator.png","signature":"1769586519817410429","tags":[]},{"attachment_folder":"","created_time":"2025-11-04T01:31:41Z","id":"96","modified_time":"2025-11-04T01:31:41Z","name":"RocketMQ.png","signature":"2062419507477567357","tags":[]},{"attachment_folder":"","created_time":"2025-11-04T01:31:41Z","id":"97","modified_time":"2025-11-04T01:31:41Z","name":"TCC.png","signature":"7197612969285998461","tags":[]},{"attachment_folder":"","created_time":"2025-11-04T01:31:41Z","id":"98","modified_time":"2025-11-04T01:31:41Z","name":"trybest.png","signature":"774460846650251133","tags":[]},{"attachment_folder":"","created_time":"2025-11-04T01:31:41Z","id":"99","modified_time":"2025-11-04T01:31:41Z","name":"XA.png","signature":"1672595627013920637","tags":[]}],"folders":[],"id":"34","modified_time":"2023-12-31T10:06:48Z","signature":"3647195760276094264","version":3}